cloudq/__init__.py
cloudq/abci.py
cloudq/agent.py
cloudq/base.py
cloudq/client.py
cloudq/common.py
cloudq/interface.py
cloudq/slurm.py
cloudq/aws/__init__.py
cloudq/aws/cloudqaws.py
cloudq/aws/utils.py
cloudq/aws/data/config.ini
cloudq/aws/data/default/add_log.py
cloudq/aws/data/default/autoexec.sh
cloudq/aws/data/default/cloud-stack.yaml
cloudq/aws/data/default/cloudq.service
cloudq/aws/data/default/cluster-config.yaml
cloudq/aws/data/default/on-compute-node-start.sh
cloudq/aws/data/default/on-head-node-start.sh
cloudq/aws/example/enable-docker/add_log.py
cloudq/aws/example/enable-docker/autoexec.sh
cloudq/aws/example/enable-docker/cloud-stack.yaml
cloudq/aws/example/enable-docker/cloudq.service
cloudq/aws/example/enable-docker/cluster-config.yaml
cloudq/aws/example/enable-docker/on-compute-node-start.sh
cloudq/aws/example/enable-docker/on-head-node-start.sh
cloudq/aws/example/enable-gpu/add_log.py
cloudq/aws/example/enable-gpu/autoexec.sh
cloudq/aws/example/enable-gpu/cloud-stack.yaml
cloudq/aws/example/enable-gpu/cloudq.service
cloudq/aws/example/enable-gpu/cluster-config.yaml
cloudq/aws/example/enable-gpu/on-compute-node-start.sh
cloudq/aws/example/enable-gpu/on-head-node-start.sh
cloudq/data/config.ini
cloudq/data/job_manifest.json
cloudq/data/project.ini
cloudq/data/resource.ini
cloudq/example/ljob_array.abci.sh
cloudq/example/ljob_pt_mnist.abci.sh
cloudq/example/ljob_tf_mnist.abci.sh
cloudq/example/mjob_array.sh
cloudq/example/mjob_pt_mnist.sh
cloudq/example/mjob_tf_mnist.sh
cloudq-1.2.0.dist-info/LICENSE.txt
cloudq-1.2.0.dist-info/METADATA
cloudq-1.2.0.dist-info/WHEEL
cloudq-1.2.0.dist-info/entry_points.txt
cloudq-1.2.0.dist-info/top_level.txt
cloudq-1.2.0.dist-info/RECORD
