Metadata-Version: 2.1
Name: cloudq
Version: 1.2.0
Summary: A cloud storage-based meta scheduler.
Home-page: https://github.com/aistairc/cloudq
Author: Shinichiro Takizawa, AIST
Author-email: shinichiro.takizawa@aist.go.jp
License: Apache License, Version 2.0
Platform: any
Classifier: Programming Language :: Python :: 3.6
Classifier: License :: OSI Approved :: Apache Software License
Classifier: Operating System :: OS Independent
Requires-Python: >=3.8
License-File: LICENSE.txt
Requires-Dist: boto3
Requires-Dist: botocore
Requires-Dist: pathos
Provides-Extra: abci
Provides-Extra: aws
Requires-Dist: pyyaml ; extra == 'aws'
Requires-Dist: Flask ; extra == 'aws'
Requires-Dist: aws-parallelcluster ; extra == 'aws'
